boxhatter/__init__.py
boxhatter/__main__.py
boxhatter/backend.py
boxhatter/common.py
boxhatter/json_schema_repo.json
boxhatter/main.py
boxhatter/server.py
boxhatter/ui.py
boxhatter/ui/main.css
boxhatter-0.2.6.dist-info/LICENSE
boxhatter-0.2.6.dist-info/METADATA
boxhatter-0.2.6.dist-info/WHEEL
boxhatter-0.2.6.dist-info/entry_points.txt
boxhatter-0.2.6.dist-info/top_level.txt
boxhatter-0.2.6.dist-info/zip-safe
boxhatter-0.2.6.dist-info/RECORD
