Metadata-Version: 2.1
Name: boxhatter
Version: 0.2.6
Summary: Continuous integration server/executor
Home-page: https://github.com/bozokopic/boxhatter
License: GPLv3
Classifier: Programming Language :: Python :: 3
Classifier: License :: OSI Approved :: GNU General Public License v3 (GPLv3)
Requires-Python: >=3.8
License-File: LICENSE
Requires-Dist: aiohttp (~=3.8.1)
Requires-Dist: appdirs (~=1.4.4)
Requires-Dist: click (~=8.0.3)
Requires-Dist: hat-aio (~=0.7.0)
Requires-Dist: hat-json (~=0.5.5)
